setup.py
autotab/__init__.py
autotab/_main.py
autotab/utils.py
autotab.egg-info/PKG-INFO
autotab.egg-info/SOURCES.txt
autotab.egg-info/dependency_links.txt
autotab.egg-info/requires.txt
autotab.egg-info/top_level.txt